examples/__init__.py
examples/all_method_complexity.py
examples/dev_data.py
examples/file_complexity.py
examples/index_all.py
examples/mine_all.py
graphrepo/__init__.py
graphrepo/config.py
graphrepo/custom_test.py
graphrepo/driller.py
graphrepo/logger.py
graphrepo/miner.py
graphrepo/singleton.py
graphrepo/utils.py
graphrepo/drillers/__init__.py
graphrepo/drillers/batch_utils.py
graphrepo/drillers/cache_driller.py
graphrepo/drillers/db_init.py
graphrepo/drillers/default.py
graphrepo/drillers/delete_all.py
graphrepo/drillers/drill_cache.py
graphrepo/drillers/driller.py
graphrepo/drillers/queue_driller.py
graphrepo/drillers/rabbit_driller.py
graphrepo/drillers/stomp_driller.py
graphrepo/mappers/__init__.py
graphrepo/mappers/csv.py
graphrepo/mappers/default.py
graphrepo/mappers/node.py
graphrepo/mappers/rels.py
graphrepo/miners/__init__.py
graphrepo/miners/commit.py
graphrepo/miners/default.py
graphrepo/miners/developer.py
graphrepo/miners/file.py
graphrepo/miners/method.py
graphrepo/miners/mine_manager.py
graphrepo/miners/utils.py
graphrepo/miners/mappers/__init__.py
graphrepo/miners/mappers/default.py
graphrepo/miners/mappers/node.py
graphrepo/miners/mappers/rels.py
graphrepo/models/__init__.py
graphrepo/models/branch.py
graphrepo/models/commit.py
graphrepo/models/custom_node.py
graphrepo/models/day.py
graphrepo/models/developer.py
graphrepo/models/file.py
graphrepo/models/method.py
graphrepo/models/month.py
graphrepo/models/relationships.py
graphrepo/models/year.py
tests/__init__.py
tests/test_cache_driller.py
tests/test_commit.py
tests/test_commit_miner.py
tests/test_csv_mapper.py
tests/test_db_init.py
tests/test_dev_miner.py
tests/test_driller.py
tests/test_file.py
tests/test_file_miner.py
tests/test_method_miner.py
tests/test_queue_driller.py
tests/test_utils.py
graphrepo-0.3.7.dist-info/LICENSE
graphrepo-0.3.7.dist-info/METADATA
graphrepo-0.3.7.dist-info/WHEEL
graphrepo-0.3.7.dist-info/top_level.txt
graphrepo-0.3.7.dist-info/RECORD
