Metadata-Version: 2.1
Name: graphrepo
Version: 0.3.7
Summary: A tool that maps a Github repo to Neo4j and Helps Mining the Repo in the DB
Home-page: https://github.com/NullConvergence/GraphRepo
License: Apache License
Platform: UNKNOWN
Requires-Python: >=3.5
Requires-Dist: lizard (==1.16.6)
Requires-Dist: pytz (==2018.9)
Requires-Dist: psutil (==5.7.0)
Requires-Dist: py2neo (==4.3.0)
Requires-Dist: pydriller (==1.15.1)
Requires-Dist: requests (==2.21.0)
Requires-Dist: pytest (==5.3.5)
Requires-Dist: GitPython (==3.1.0)
Requires-Dist: PyYAML (==5.3.1)
Requires-Dist: diskcache (==4.1.0)
Requires-Dist: pika (==1.1.0)
Requires-Dist: stomp.py (==6.1.0)
